counter.v
// counter.v
module counter(
    input clk,
    input rst,
    output reg [3:0] q
);

    always @(posedge clk or posedge rst) begin
        if (rst)
            q <= 0;
        else
            q <= q + 1;
    end

endmodule

tb_counter.v
`timescale 1ns/1ps

module tb_counter;
    reg clk;
    reg rst;
    wire [3:0] q;

    // Instanza del modulo counter
    counter uut (
        .clk(clk),
        .rst(rst),
        .q(q)
    );

    // Generatore di clock
    initial clk = 0;
    always #5 clk = ~clk;  // clock con periodo di 10 ns

    // Stimoli
    initial begin
        $dumpfile("dump.vcd");   // file per GTKWave
        $dumpvars(0, tb_counter);

        rst = 1;                  // inizio con reset
        #10 rst = 0;              // rimuove reset dopo 10 ns
        #100 $finish;             // termina simulazione dopo 100 ns
    end
endmodule

dump.vcd
$date
	Fri Sep 12 22:08:39 2025
$end
$version
	Icarus Verilog
$end
$timescale
	1ps
$end
$scope module tb_counter $end
$var wire 4 ! q [3:0] $end
$var reg 1 " clk $end
$var reg 1 # rst $end
$scope module uut $end
$var wire 1 " clk $end
$var wire 1 # rst $end
$var reg 4 $ q [3:0] $end
$upscope $end
$upscope $end
$enddefinitions $end
#0
$dumpvars
b0 $
1#
0"
b0 !
$end
#5000
1"
#10000
0"
0#
#15000
b1 !
b1 $
1"
#20000
0"
#25000
b10 !
b10 $
1"
#30000
0"
#35000
b11 !
b11 $
1"
#40000
0"
#45000
b100 !
b100 $
1"
#50000
0"
#55000
b101 !
b101 $
1"
#60000
0"
#65000
b110 !
b110 $
1"
#70000
0"
#75000
b111 !
b111 $
1"
#80000
0"
#85000
b1000 !
b1000 $
1"
#90000
0"
#95000
b1001 !
b1001 $
1"
#100000
0"
#105000
b1010 !
b1010 $
1"
